{
  "item-states": [
    {
      "folded": true,
      "id": "ba8ADKmh5DCZPrM5fP5Che"
    },
    {
      "folded": true,
      "id": "a2FzZwwjJEFJEEznZpbCys"
    },
    {
      "folded": true,
      "id": "36QwJeNipGoauymBM3+sRH"
    },
    {
      "folded": true,
      "id": "b1LhwjwRtEMK+s78iist46"
    },
    {
      "folded": false,
      "id": "49TE5ChJ5FMYn8C4B1kUnO"
    },
    {
      "folded": true,
      "id": "97XHHpQhBOR6uFXkUm9VFW"
    },
    {
      "folded": false,
      "id": "c8rX+Hf8xDc6keiXg4q2mN"
    }
  ]
}